{
  "type": "minecraft:smithing_transform",
  "addition": "minecraft:prismarine_shard",
  "base": "minecraft:golden_axe",
  "result": {
    "count": 1,
    "id": "minecraft:golden_axe",
    "components": {
      "minecraft:item_model": "vanilla_enhanced:golden_axe_wayfinder_and_prismarine_trim",
      "minecraft:trim": {
        "material": "vanilla_enhanced:prismarine",
        "pattern": "minecraft:wayfinder"
      }
    }
  },
  "template": "minecraft:wayfinder_armor_trim_smithing_template"
}