{
  "type": "minecraft:smithing_transform",
  "addition": {
    "item": "minecraft:heart_of_the_sea"
  },
  "base": {
    "item": "minecraft:wooden_shovel"
  },
  "result": {
    "count": 1,
    "id": "minecraft:wooden_shovel",
    "components": {
      "minecraft:custom_model_data": 63,
      "minecraft:trim": {
        "material": "vanilla_enhanced:heart_of_the_sea",
        "pattern": "minecraft:vex"
      }
    }
  },
  "template": {
    "item": "minecraft:vex_armor_trim_smithing_template"
  }
}